OMTF/__init__.py
OMTF/Brokers/__init__.py
OMTF/Brokers/binance_broker.py
OMTF/Brokers/degiro.py
OMTF/Brokers/metatrader.py
OMTF/DataProviders/__init__.py
OMTF/DataProviders/aemet.py
OMTF/DataProviders/benzinga.py
OMTF/DataProviders/coingecko.py
OMTF/DataProviders/coinmarketcap.py
OMTF/DataProviders/data.py
OMTF/DataProviders/dilutionTracker.py
OMTF/DataProviders/expansion.py
OMTF/DataProviders/finviz.py
OMTF/DataProviders/floatChecker.py
OMTF/DataProviders/fmp.py
OMTF/DataProviders/fxstreet.py
OMTF/DataProviders/geonames.py
OMTF/DataProviders/inversis_todo.py
OMTF/DataProviders/marketWatch.py
OMTF/DataProviders/oecd.py
OMTF/DataProviders/openstreetmap.py
OMTF/DataProviders/polygon.py
OMTF/DataProviders/sec.py
OMTF/DataProviders/tradingterminal.py
OMTF/DataProviders/worldBank.py
OMTF/DataProviders/worldHealthOrg.py
OMTF/DataProviders/world_population.py
OMTF/DataProviders/yahoo.py
OMTF/MachineLearning/00_models_comparison.py
OMTF/MachineLearning/RandomForest.py
OMTF/MachineLearning/__init__.py
OMTF/MachineLearning/decision_trees.py
OMTF/MachineLearning/genetic_algorithm.py
OMTF/MachineLearning/gradientboosting.py
OMTF/MachineLearning/k_nearest_neighbors.py
OMTF/MachineLearning/kmeans_clustering.py
OMTF/MachineLearning/linear_regression.py
OMTF/MachineLearning/logistic_regression.py
OMTF/MachineLearning/long_short_term_memory.py
OMTF/MachineLearning/naive_bayes.py
OMTF/MachineLearning/neural_networks.py
OMTF/MachineLearning/principal_component.py
OMTF/MachineLearning/random_forest.py
OMTF/MachineLearning/recurrent_neural_networks.py
OMTF/MachineLearning/support_vector.py
OMTF/MachineLearning/utils.py
OMTF/MachineLearning/xgboost_model.py
OMTF/Trading/KEYS.py
OMTF/Trading/__init__.py
OMTF/Trading/asset_tradeablitiy.py
OMTF/Trading/backtest.py
OMTF/Trading/backtest_utils.py
OMTF/Trading/config.py
OMTF/Trading/continuous_backtest.py
OMTF/Trading/discrete_backtest.py
OMTF/Trading/execution.py
OMTF/Trading/execution_utils.py
OMTF/Trading/indicators.py
OMTF-1.0.4.dist-info/LICENSE
OMTF-1.0.4.dist-info/METADATA
OMTF-1.0.4.dist-info/WHEEL
OMTF-1.0.4.dist-info/top_level.txt
OMTF-1.0.4.dist-info/RECORD
